{
  "configurations": [
	{
	  "name": "x64-Debug",
	  "generator": "Ninja",
	  "configurationType": "Debug",
	  "inheritEnvironments": [ "msvc_x64_x64" ],
	  "buildRoot": "${projectDir}\\out\\build\\${name}",
	  "installRoot": "${projectDir}\\out\\install\\${name}",
	  "cmakeCommandArgs": "",
	  "buildCommandArgs": "",
	  "ctestCommandArgs": "",
	  "variables": [
		{
		  "name": "USE_WINDOWS_SUBSYSTEM",
		  "value": "False",
		  "type": "BOOL"
		},
		{
		  "name": "ENGINE_EDITOR",
		  "value": "True",
		  "type": "BOOL"
		}
	  ]
	},
	{
	  "name": "x64-Release",
	  "generator": "Ninja",
	  "configurationType": "Release",
	  "buildRoot": "${projectDir}\\out\\build\\${name}",
	  "installRoot": "${projectDir}\\out\\install\\${name}",
	  "cmakeCommandArgs": "",
	  "buildCommandArgs": "",
	  "ctestCommandArgs": "",
	  "inheritEnvironments": [ "msvc_x64_x64" ],
	  "variables": [
		{
		  "name": "USE_WINDOWS_SUBSYSTEM",
		  "value": "False",
		  "type": "BOOL"
		},
		{
		  "name": "ENGINE_EDITOR",
		  "value": "True",
		  "type": "BOOL"
		}
	  ]
	},
	{
	  "name": "WSL-GCC-Release",
	  "generator": "Ninja",
	  "configurationType": "Release",
	  "buildRoot": "${projectDir}\\out\\build\\${name}",
	  "installRoot": "${projectDir}\\out\\install\\${name}",
	  "cmakeExecutable": "cmake",
	  "cmakeCommandArgs": "",
	  "buildCommandArgs": "",
	  "ctestCommandArgs": "",
	  "inheritEnvironments": [ "linux_x64" ],
	  "wslPath": "${defaultWSLPath}",
	  "variables": [
		{
		  "name": "ENGINE_EDITOR",
		  "value": "False",
		  "type": "BOOL"
		}
	  ]
	}
  ]
}